setup.py
dist_prob_gb/Binomialdistribution.py
dist_prob_gb/Gaussiandistribution.py
dist_prob_gb/Generaldistribution.py
dist_prob_gb/__init__.py
dist_prob_gb.egg-info/PKG-INFO
dist_prob_gb.egg-info/SOURCES.txt
dist_prob_gb.egg-info/dependency_links.txt
dist_prob_gb.egg-info/not-zip-safe
dist_prob_gb.egg-info/top_level.txt