Metadata-Version: 1.0
Name: dist-prob-gb
Version: 1.0
Summary: Gaussian and Binomial distributions
Home-page: UNKNOWN
Author: Ismail Musharaf
Author-email: ismailmushraf@gmail.com
License: UNKNOWN
Platform: UNKNOWN
